fish/__init__.py
fish/_all_.py
fish/database.py
fish/foo.py
fish/pathopen.py
fish/screen.py
fish/transform.py
fish/animate/__init__.py
fish/animate/general.py
fish/animate/person.py
fish/console/__init__.py
fish/console/color.py
fish/engine/__init__.py
fish/engine/movement.py
fish/gui/__init__.py
fish/gui/button.py
fish/gui/gallery.py
fish/gui/inp.py
fish/gui/label.py
fish/gui/left.png
fish/gui/right.png
fish_all-0.0.9.dist-info/LICENSE
fish_all-0.0.9.dist-info/METADATA
fish_all-0.0.9.dist-info/WHEEL
fish_all-0.0.9.dist-info/top_level.txt
fish_all-0.0.9.dist-info/RECORD
