Metadata-Version: 2.1
Name: fish-all
Version: 0.0.9
Summary: This projekt is made by an amateour and is made for small uses
Home-page: UNKNOWN
Author: Valter Daugberg
Author-email: valteryde@hotmail.com
License: UNKNOWN
Platform: UNKNOWN
Classifier: Programming Language :: Python :: 3
Classifier: License :: OSI Approved :: MIT License
Classifier: Operating System :: OS Independent
Requires-Python: >=3.6
